recce_cloud/VERSION
recce_cloud/__init__.py
recce_cloud/artifact.py
recce_cloud/cli.py
recce_cloud/delete.py
recce_cloud/download.py
recce_cloud/report.py
recce_cloud/review.py
recce_cloud/upload.py
recce_cloud/api/__init__.py
recce_cloud/api/base.py
recce_cloud/api/client.py
recce_cloud/api/exceptions.py
recce_cloud/api/factory.py
recce_cloud/api/github.py
recce_cloud/api/gitlab.py
recce_cloud/auth/__init__.py
recce_cloud/auth/callback_server.py
recce_cloud/auth/login.py
recce_cloud/auth/profile.py
recce_cloud/auth/templates/error.html
recce_cloud/auth/templates/success.html
recce_cloud/ci_providers/__init__.py
recce_cloud/ci_providers/base.py
recce_cloud/ci_providers/detector.py
recce_cloud/ci_providers/github_actions.py
recce_cloud/ci_providers/gitlab_ci.py
recce_cloud/commands/__init__.py
recce_cloud/commands/diagnostics.py
recce_cloud/config/__init__.py
recce_cloud/config/project_config.py
recce_cloud/config/resolver.py
recce_cloud/services/__init__.py
recce_cloud/services/diagnostic_service.py
recce_cloud_nightly-1.32.0.20260129.dist-info/METADATA
recce_cloud_nightly-1.32.0.20260129.dist-info/WHEEL
recce_cloud_nightly-1.32.0.20260129.dist-info/entry_points.txt
recce_cloud_nightly-1.32.0.20260129.dist-info/RECORD
